setup.cfg
setup.py
tgcurvycorners/__init__.py
tgcurvycorners/widgets.py
tgcurvycorners.egg-info/PKG-INFO
tgcurvycorners.egg-info/SOURCES.txt
tgcurvycorners.egg-info/dependency_links.txt
tgcurvycorners.egg-info/entry_points.txt
tgcurvycorners.egg-info/not-zip-safe
tgcurvycorners.egg-info/requires.txt
tgcurvycorners.egg-info/top_level.txt
tgcurvycorners/static/javascript/rounded_corners.inc.js
tgcurvycorners/static/javascript/rounded_corners_lite.inc.js
