Metadata-Version: 1.0
Name: tgcurvycorners
Version: 0.1.1
Summary: A TurboGears Widget to help use curvycorners
Home-page: UNKNOWN
Author: Florent Aide
Author-email: florent.aide@gmail.com
License: MIT or PSF
Keywords: turbogears.widgets
Platform: UNKNOWN
Classifier: Development Status :: 3 - Alpha
Classifier: Operating System :: OS Independent
Classifier: Programming Language :: Python
Classifier: Topic :: Software Development :: Libraries :: Python Modules
Classifier: Framework :: TurboGears
Classifier: Framework :: TurboGears :: Widgets
